{
    "type": "origins:effect_immunity",
    "effects": [
        "minecraft:strength",
        "minecraft:regeneration",
        "minecraft:poison",
        "minecraft:resistance",
        "minecraft:slowness",
        "minecraft:fire_resistance",
        "minecraft:slowfall",
        "minecraft:levitation",
        "minecraft:jump_boost"
    ],
    "condition": {
        "type": "origins:power_active",
        "power": "roubar:phantomize"
    },
    "name": "Hollow Muscles?!?!?!?!",
    "description": "Status effects fall off when you phantomize."
}